<?xml version="1.0" encoding="UTF-8"?><oai_dc:dc xmlns:oai_dc="http://www.openarchives.org/OAI/2.0/oai_dc/" xmlns:dc="http://purl.org/dc/elements/1.1/" xmlns:xsi="http://www.w3.org/2001/XMLSchema-instance" xsi:schemaLocation="http://www.openarchives.org/OAI/2.0/oai_dc/ http://www.openarchives.org/OAI/2.0/oai_dc.xsd">
  <dc:creator>Pascual Sanz, Carlos</dc:creator>
  <dc:creator>Estrada Marcén, Nerea</dc:creator>
  <dc:title>Motivación, práctica deportiva y rendimiento académico en Educación Física</dc:title>
  <dc:identifier>http://zaguan.unizar.es/record/31637</dc:identifier>
  <dc:publisher>Universidad de Zaragoza</dc:publisher>
  <dc:date>2015</dc:date>
  <dc:description>En este estudio se ha analizado a una muestra de estudiantes de 3º de ESO con el fin de conocer su perfil motivacional, su nivel de práctica deportiva extraescolar y su rendimiento académico, todo ello en Educación Física, así como para identificar diferencias entre sexos en estos campos estudiados y conocer las diferentes relaciones que se pueden dar entre los mismos. Se ha utilizado el cuestionario MSLQ para recopilar los datos correspondientes al perfil motivacional del alumnado.</dc:description>
  <dc:format>pdf</dc:format>
  <dc:language>spa</dc:language>
  <dc:type>info:eu-repo/semantics/masterThesis</dc:type>
  <dc:rights>by-nc-sa</dc:rights>
  <dc:rights>http://creativecommons.org/licenses/by-nc-sa/3.0/</dc:rights>
</oai_dc:dc>