<?xml version="1.0" encoding="UTF-8"?><oai_dc:dc xmlns:oai_dc="http://www.openarchives.org/OAI/2.0/oai_dc/" xmlns:dc="http://purl.org/dc/elements/1.1/" xmlns:xsi="http://www.w3.org/2001/XMLSchema-instance" xsi:schemaLocation="http://www.openarchives.org/OAI/2.0/oai_dc/ http://www.openarchives.org/OAI/2.0/oai_dc.xsd">
  <dc:creator>Delgado Valdivieso, Nagore</dc:creator>
  <dc:creator>Fraj Andrés, Elena</dc:creator>
  <dc:title>Consecuencias de las prácticas engañosas del Marketing y la Responsabilidad Social Corporativa</dc:title>
  <dc:identifier>http://zaguan.unizar.es/record/65141</dc:identifier>
  <dc:publisher>Universidad de Zaragoza</dc:publisher>
  <dc:date>2017</dc:date>
  <dc:description>La responsabilidad social corporativa es un tema que cada vez está más en auge, debido al aumento de la concienciación de la población sobre las consecuencias de las actividades económicas y por la evolución del consumidor, hacia clientes más exigentes que buscan el valor añadido de los productos. A pesar de esto, existen empresas que sólo buscan su propio beneficio sin reparar en las consecuencias de sus acciones. Por ello en este trabajo, se analiza las consecuencias y efectos que tienen dichas prácticas para el consumidor, empresas competidores y para la sociedad. Para averiguar dichas consecuencias, la opinión que poseen los consumidores en la actualidad sobre estas acciones poco éticas y las ventajas de ser una empresa responsable se ha realizado un análisis teórico y un grupo de discusión. En definitiva, podemos ver la relación entre las prácticas engañosas del marketing y su relación con la responsabilidad social corporativa.</dc:description>
  <dc:format>pdf</dc:format>
  <dc:language>spa</dc:language>
  <dc:type>info:eu-repo/semantics/bachelorThesis</dc:type>
  <dc:rights>by-nc-sa</dc:rights>
  <dc:rights>http://creativecommons.org/licenses/by-nc-sa/3.0/</dc:rights>
</oai_dc:dc>