<?xml version="1.0" encoding="UTF-8"?><oai_dc:dc xmlns:oai_dc="http://www.openarchives.org/OAI/2.0/oai_dc/" xmlns:dc="http://purl.org/dc/elements/1.1/" xmlns:xsi="http://www.w3.org/2001/XMLSchema-instance" xsi:schemaLocation="http://www.openarchives.org/OAI/2.0/oai_dc/ http://www.openarchives.org/OAI/2.0/oai_dc.xsd">
  <dc:creator>Calvo Labat, Javier</dc:creator>
  <dc:creator>Blesa, Túa</dc:creator>
  <dc:title>Pasión de muerte y primavera: una lectura de la obra de Miguel Labordeta</dc:title>
  <dc:identifier>http://zaguan.unizar.es/record/9656</dc:identifier>
  <dc:subject>Miguel Labordeta</dc:subject>
  <dc:publisher>Universidad de Zaragoza</dc:publisher>
  <dc:date>2012</dc:date>
  <dc:description>En la tesina se propone una lectura de la obra de Miguel Labordeta bajo un enfoque psicoanalítico. Centrándonos especialmente en su pasión por la vida y la muerte (en el poeta encontramos una marcada atracción por el suicidio), hemos intentado apoyarnos en algunos conceptos freudianos que puedan explicar la aparición conjunta de ambas pasiones, en principio irreconciliables; así como hemos tratado de descomponer los diferentes elementos del mundo y la retórica que Miguel Labordeta usó para su expresión.</dc:description>
  <dc:format>pdf</dc:format>
  <dc:language>spa</dc:language>
  <dc:type>info:eu-repo/semantics/masterThesis</dc:type>
  <dc:rights>by-nc-sa</dc:rights>
  <dc:rights>http://creativecommons.org/licenses/by-nc-sa/3.0/</dc:rights>
</oai_dc:dc>