<?xml version="1.0" encoding="UTF-8"?><oai_dc:dc xmlns:oai_dc="http://www.openarchives.org/OAI/2.0/oai_dc/" xmlns:dc="http://purl.org/dc/elements/1.1/" xmlns:xsi="http://www.w3.org/2001/XMLSchema-instance" xsi:schemaLocation="http://www.openarchives.org/OAI/2.0/oai_dc/ http://www.openarchives.org/OAI/2.0/oai_dc.xsd">
  <dc:creator>Luzón Gil, Jorge</dc:creator>
  <dc:creator>Rodríguez Casals, Carlos</dc:creator>
  <dc:title>Trabajo Fin de Máster en la Especialidad de Procesos Químicos</dc:title>
  <dc:identifier>http://zaguan.unizar.es/record/9353</dc:identifier>
  <dc:publisher>Universidad de Zaragoza</dc:publisher>
  <dc:date>2012</dc:date>
  <dc:description>Se ha realizado una memoria con carácter integrador que moviliza el conjunto de competencias que he desarrollado a lo largo de mi proceso formativo durante todo el curso lectivo. En él se analizan tres documentos principales: la programación didáctica, la unidad de trabajo y el proyecto de innovación y las relaciones existentes entre ellos a través de un proceso reflexivo para justificar la adquisición de la competencias que marca la guía docente.</dc:description>
  <dc:format>pdf</dc:format>
  <dc:language>spa</dc:language>
  <dc:type>info:eu-repo/semantics/masterThesis</dc:type>
  <dc:rights>by-nc-sa</dc:rights>
  <dc:rights>http://creativecommons.org/licenses/by-nc-sa/3.0/</dc:rights>
</oai_dc:dc>