<?xml version="1.0" encoding="UTF-8"?><oai_dc:dc xmlns:oai_dc="http://www.openarchives.org/OAI/2.0/oai_dc/" xmlns:dc="http://purl.org/dc/elements/1.1/" xmlns:xsi="http://www.w3.org/2001/XMLSchema-instance" xsi:schemaLocation="http://www.openarchives.org/OAI/2.0/oai_dc/ http://www.openarchives.org/OAI/2.0/oai_dc.xsd">
  <dc:creator>González Berna, Javier</dc:creator>
  <dc:creator>Oliete Terraz, Patricia</dc:creator>
  <dc:creator>Mesa Capapé, M. Cristina</dc:creator>
  <dc:title>Procesado, microestructura y propiedades ópticas de fibras cerámicas eutécticas Al2O3 - GdAlO3 : Eu 3+</dc:title>
  <dc:identifier>http://zaguan.unizar.es/record/6335</dc:identifier>
  <dc:publisher>Universidad de Zaragoza</dc:publisher>
  <dc:date>2011</dc:date>
  <dc:description>Este proyecto tiene como objetivo el estudio de barras eutécticas Al2O3-GdAlO3 dopadas con europio procesadas por fusión zonal con láser. Se ha procesado a distintas velocidades de procesado para ver el efecto en la microestructura y propiedades ópticas. La caracterización de la microestructura se ha realizado utilizando el microscopio electrónico de barrido y el comportamiento óptico a partir de experimentos de emisión y excitación.</dc:description>
  <dc:format>pdf</dc:format>
  <dc:language>spa</dc:language>
  <dc:type>info:eu-repo/semantics/masterThesis</dc:type>
  <dc:rights>by-nc-sa</dc:rights>
  <dc:rights>http://creativecommons.org/licenses/by-nc-sa/3.0/</dc:rights>
</oai_dc:dc>