<?xml version="1.0" encoding="UTF-8"?><oai_dc:dc xmlns:oai_dc="http://www.openarchives.org/OAI/2.0/oai_dc/" xmlns:dc="http://purl.org/dc/elements/1.1/" xmlns:xsi="http://www.w3.org/2001/XMLSchema-instance" xsi:schemaLocation="http://www.openarchives.org/OAI/2.0/oai_dc/ http://www.openarchives.org/OAI/2.0/oai_dc.xsd">
  <dc:creator>Martínez Ubide, Pablo</dc:creator>
  <dc:creator>Guerrero Iturbe, Jesús</dc:creator>
  <dc:title>Cartografía de movimientos de ladera en el valle del Bolática como herramienta de gestión para una posible ampliación de la Estación de Esquí de Panticosa (Alto valle del Gállego, Pirineo Aragonés)</dc:title>
  <dc:identifier>http://zaguan.unizar.es/record/64153</dc:identifier>
  <dc:publisher>Universidad de Zaragoza</dc:publisher>
  <dc:date>2017</dc:date>
  <dc:description>El presente trabajo de fin de grado pretende evaluar la susceptibilidad y la amenaza de movimientos de ladera en un ámbito local situado en las proximidades del pueblo de Panticosa en el valle de Tena. Para ello, se ha realizado una cartografía de los elementos geomorfológicos al Este de la Estación de Esquí de Panticosa en el valle del río Bolática. Los resultados tienen un interés especial por la aproximación de la estación de esquí de Panticosa, situada en el valle colindante a la zona de estudio propuesta. Gracias al modelo de susceptibilidad que ha resultado satisfactorio para la realización de los remontes con seguridad pero no con toda la certeza de ser viable por el riesgo de aludes en la ladera.</dc:description>
  <dc:format>pdf</dc:format>
  <dc:language>spa</dc:language>
  <dc:type>info:eu-repo/semantics/bachelorThesis</dc:type>
  <dc:rights>by-nc-sa</dc:rights>
  <dc:rights>http://creativecommons.org/licenses/by-nc-sa/3.0/</dc:rights>
</oai_dc:dc>