<?xml version="1.0" encoding="UTF-8"?><oai_dc:dc xmlns:oai_dc="http://www.openarchives.org/OAI/2.0/oai_dc/" xmlns:dc="http://purl.org/dc/elements/1.1/" xmlns:xsi="http://www.w3.org/2001/XMLSchema-instance" xsi:schemaLocation="http://www.openarchives.org/OAI/2.0/oai_dc/ http://www.openarchives.org/OAI/2.0/oai_dc.xsd">
  <dc:creator>González Colás, Marcos</dc:creator>
  <dc:creator>Bambó Naya, Raimundo</dc:creator>
  <dc:title>Tiempo y ritmo en la obra de Cedric Price</dc:title>
  <dc:identifier>http://zaguan.unizar.es/record/47517</dc:identifier>
  <dc:publisher>Universidad de Zaragoza</dc:publisher>
  <dc:date>2015</dc:date>
  <dc:description>La figura del arquitecto británico Cedric Price (1934-2003) ha conformado un legado arquitectónico radical y original. El presente estudio trata de desentrañar su particular visión sobre la arquitectura mediante un aspecto fundamental de la misma: la cuarta dimensión, el tiempo. El tiempo es una variable de gran fuerza en la arquitectura de Price, que irá mutando a lo largo de su trayectoria hasta la exposición MEAN (TIME) donde clasifica el tiempo en catorce categorías. Estas categorías establecen el hilo conductor en el análisis del caso de estudio, la propuesta no construida STEEL HOUSE, concurso celebrado en el año 1966, que continuaría desarrollando en HOUSING RESEARCH, donde el aspecto temporal tiene gran importancia.</dc:description>
  <dc:format>pdf</dc:format>
  <dc:language>spa</dc:language>
  <dc:type>info:eu-repo/semantics/bachelorThesis</dc:type>
  <dc:rights>by-nc-sa</dc:rights>
  <dc:rights>http://creativecommons.org/licenses/by-nc-sa/3.0/</dc:rights>
</oai_dc:dc>